snowflake.pth
snowflake/_legacy/__init__.py
snowflake_legacy-0.13.1.dist-info/METADATA
snowflake_legacy-0.13.1.dist-info/WHEEL
snowflake_legacy-0.13.1.dist-info/RECORD
